pytest_embrace/__init__.py
pytest_embrace/anno.py
pytest_embrace/case.py
pytest_embrace/codegen.py
pytest_embrace/embrace.py
pytest_embrace/exc.py
pytest_embrace/loader.py
pytest_embrace/plugin.py
pytest_embrace/py.typed
pytest_embrace/test_undot.py
pytest_embrace/undot.py
pytest_embrace-4.0.0.dist-info/METADATA
pytest_embrace-4.0.0.dist-info/WHEEL
pytest_embrace-4.0.0.dist-info/entry_points.txt
pytest_embrace-4.0.0.dist-info/RECORD
